rixstoolbox/__init__.py
rixstoolbox/math.py
rixstoolbox-0.1.0.dist-info/METADATA
rixstoolbox-0.1.0.dist-info/WHEEL
rixstoolbox-0.1.0.dist-info/top_level.txt
rixstoolbox-0.1.0.dist-info/RECORD
