Metadata-Version: 2.1
Name: rixstoolbox
Version: 0.1.0
Summary: Python package for analysis of ESRF ID32 RIXS data
Home-page: https://github.com/kkummer/RixsToolBox
Author: Kurt Kummer
License: MIT
Classifier: Development Status :: 1 - Planning
Classifier: Intended Audience :: Science/Research
Requires-Dist: numpy
